{"backdrop_path":null,"created_by":[],"episode_run_time":[],"first_air_date":"2019-03-19","genres":[],"homepage":"","id":101129,"in_production":true,"languages":[],"last_air_date":"2019-03-19","last_episode_to_air":{"air_date":"2019-03-19","episode_number":1,"id":2203686,"name":"Episode 1","overview":"Episode 1 by gangatv","production_code":"","season_number":1,"show_id":101129,"still_path":null,"vote_average":0.0,"vote_count":0},"name":"Alerta Aeropuerto","next_episode_to_air":null,"networks":[],"number_of_episodes":1,"number_of_seasons":1,"origin_country":[],"original_language":"en","original_name":"Alerta Aeropuerto","overview":"Tv show by gangatv","popularity":2.668,"poster_path":"/eLV98ObmZ81hHWGJdOulC2Esauu.jpg","production_companies":[],"seasons":[{"air_date":"2019-03-19","episode_count":1,"id":146311,"name":"Season 1","overview":"","poster_path":null,"season_number":1}],"status":"Returning Series","type":"Scripted","vote_average":7.1,"vote_count":52}