{"backdrop_path":null,"created_by":[{"id":17735,"credit_id":"5257fc0219c29531db307fed","name":"Mike White","gender":2,"profile_path":"/eJpW9GKmWh0W7enmjjZQ8MIEzoI.jpg"}],"episode_run_time":[30],"first_air_date":"2004-03-09","genres":[{"id":35,"name":"Comedy"}],"homepage":"","id":10063,"in_production":false,"languages":["en"],"last_air_date":"2004-04-05","last_episode_to_air":{"air_date":"2004-04-05","episode_number":6,"id":416620,"name":"Prom Night","overview":"Ted invites Lesley's old high school prom date to their home after Ben learns that Ted is still jealous of him. Liam is asked to chaperone Chloe, Preston and their dates to the prom.","production_code":"","season_number":1,"show_id":10063,"still_path":null,"vote_average":0.0,"vote_count":0},"name":"Cracking Up","next_episode_to_air":null,"networks":[{"name":"FOX","id":19,"logo_path":"/1DSpHrWyOORkL9N2QHX7Adt31mQ.png","origin_country":"US"}],"number_of_episodes":12,"number_of_seasons":1,"origin_country":["US"],"original_language":"en","original_name":"Cracking Up","overview":"Cracking Up is an American television sitcom created by School of Rock writer Mike White, who also served as the series' head writer. It aired on the Fox Network on Monday nights from March to May 2004. The title of the program and the name of the psychiatrist, Dr. Bollas, are comic allusions to Christopher Bollas, a psychoanalyst, and to his book Cracking UP.","popularity":2.841,"poster_path":"/ehspQz3SRThdYy9qbs9DdOwG21g.jpg","production_companies":[],"seasons":[{"air_date":null,"episode_count":1,"id":20002,"name":"Specials","overview":"","poster_path":null,"season_number":0},{"air_date":"2004-03-09","episode_count":12,"id":20001,"name":"Season 1","overview":"","poster_path":null,"season_number":1}],"status":"Ended","type":"Scripted","vote_average":5.0,"vote_count":1}