{"backdrop_path":null,"created_by":[],"episode_run_time":[],"first_air_date":"2017-11-22","genres":[],"homepage":"","id":103676,"in_production":true,"languages":[],"last_air_date":"2017-11-22","last_episode_to_air":{"air_date":"2017-11-22","episode_number":1,"id":2277067,"name":"Colors","overview":"Simple songs mixed","production_code":"","season_number":1,"show_id":103676,"still_path":null,"vote_average":0.0,"vote_count":0},"name":"Learning Songs by Little Baby Bum  Nursery Rhyme Friends","next_episode_to_air":null,"networks":[],"number_of_episodes":1,"number_of_seasons":1,"origin_country":[],"original_language":"en","original_name":"Learning Songs by Little Baby Bum  Nursery Rhyme Friends","overview":"Simple songs mixed with bright and colourful animations for young kids to learn about the vibrant world around them. Together they explore colours, animals, numbers, and vehicles.","popularity":0.6,"poster_path":"/t0SqkbbPBtdgvNArw9hDu2uXqYh.jpg","production_companies":[],"seasons":[{"air_date":"2017-11-22","episode_count":1,"id":151315,"name":"Season 1","overview":"","poster_path":null,"season_number":1}],"status":"Returning Series","type":"Scripted","vote_average":0.0,"vote_count":0}