{"backdrop_path":"/xJvMcRLNWbpNk4GVUV1rewS17j5.jpg","created_by":[],"episode_run_time":[],"first_air_date":"2018-12-21","genres":[],"homepage":"","id":102724,"in_production":false,"languages":["fa"],"last_air_date":"2018-12-21","last_episode_to_air":{"air_date":"2018-12-21","episode_number":1,"id":2243402,"name":"klk Sheshom 01","overview":"klk Sheshom Episode 1","production_code":"","season_number":1,"show_id":102724,"still_path":null,"vote_average":0.0,"vote_count":0},"name":"klk Sheshom","next_episode_to_air":null,"networks":[],"number_of_episodes":1,"number_of_seasons":1,"origin_country":[],"original_language":"fa","original_name":"کلک ششم","overview":"Synopsis !\n\nThe sixth trick series is the story of Khosr's legacy, which is told in the language of satire and sugar on the lips of four grooms and their daughters.\n\n  The groom prays for his death, the fringes of the competitive life of the four booths and the four sisters of the story's satire, and conveys the identity of the heritage in serious language by the character of a wise old man.\n\nEach has its own plan to get more capital, unaware that there is a sixth trick in the story.\n\nSerial message!\n\nLet's turn unnecessary competitions into friendships!","popularity":0.6,"poster_path":"/vtm9FggmOD2NLfb7eUnwJnWkGt3.jpg","production_companies":[],"seasons":[{"air_date":"2018-12-21","episode_count":1,"id":149343,"name":"Season 1","overview":"","poster_path":null,"season_number":1}],"status":"Ended","type":"Scripted","vote_average":0.0,"vote_count":0}