{"backdrop_path":null,"created_by":[],"episode_run_time":[60],"first_air_date":null,"genres":[{"id":10759,"name":"Action & Adventure"}],"homepage":"","id":10261,"in_production":true,"languages":["en"],"last_air_date":null,"last_episode_to_air":null,"name":"Celebrity Boxing","next_episode_to_air":null,"networks":[{"name":"FOX","id":19,"logo_path":"/1DSpHrWyOORkL9N2QHX7Adt31mQ.png","origin_country":"US"}],"number_of_episodes":0,"number_of_seasons":0,"origin_country":["US"],"original_language":"en","original_name":"Celebrity Boxing","overview":"Celebrity Boxing was a FOX television show, in which celebrities whose careers and/or notoriety had diminished were pitted against each other in exhibition boxing matches. The contestants wore headgear during the fights, which were scheduled for three rounds apiece. Two episodes of the show were aired.\n\nIn 2002, TV Guide ranked it number 6 on its TV Guide's 50 Worst TV Shows of All Time list.","popularity":0.6,"poster_path":null,"production_companies":[],"seasons":[],"status":"Ended","type":"Scripted","vote_average":3.0,"vote_count":1}