{"backdrop_path":null,"created_by":[{"id":12115,"credit_id":"5257feb519c29531db338c61","name":"Steven Bochco","gender":2,"profile_path":"/7xzmxnzITBVY2Y8XO5hRYzeu59g.jpg"},{"id":933119,"credit_id":"5257feb519c29531db338c67","name":"William M. Finkelstein","gender":2,"profile_path":"/xmYGSzzQcD7MX2OPcqlTLKCIQ7I.jpg"}],"episode_run_time":[60],"first_air_date":"1990-09-26","genres":[{"id":18,"name":"Drama"}],"homepage":"","id":10242,"in_production":true,"languages":["en"],"last_air_date":"1990-12-26","last_episode_to_air":{"air_date":"1990-12-26","episode_number":11,"id":421655,"name":"Bang the Potts Slowly","overview":"Larusso returns to the force, Quinn reflects on the end of her marriage,Mayor Plank renews her run for the Senate, and a serial rapist outwits detectives.","production_code":"","season_number":1,"show_id":10242,"still_path":"/x4CAfh5DnBfisaZCaU6ndrGChQ7.jpg","vote_average":0.0,"vote_count":0},"name":"Cop Rock","next_episode_to_air":null,"networks":[{"name":"ABC","id":2,"logo_path":"/ndAvF4JLsliGreX87jAc9GdjmJY.png","origin_country":"US"}],"number_of_episodes":11,"number_of_seasons":1,"origin_country":["US"],"original_language":"en","original_name":"Cop Rock","overview":"Cop Rock is an Emmy Award-winning American musical police drama series that aired on ABC in 1990. The show, a police drama presented as a musical, was co-created by Steven Bochco, who also served as executive producer. TV Guide ranked it #8 on TV Guide's List of the 50 Worst TV Shows of All Time list in 2002. The periodical dubbed it \"the single most bizarre TV musical of all time.\"","popularity":1.641,"poster_path":null,"production_companies":[],"seasons":[{"air_date":"1990-09-26","episode_count":11,"id":20261,"name":"Season 1","overview":"","poster_path":null,"season_number":1}],"status":"Ended","type":"Scripted","vote_average":4.0,"vote_count":2}