{"backdrop_path":"/z9QAsYCEv407wa2yv3LlDBCMxGT.jpg","created_by":[{"id":2626744,"credit_id":"5eb1b21f00fb6b001eea42df","name":"Krunoslav Trninić","gender":2,"profile_path":null}],"episode_run_time":[18],"first_air_date":"2019-09-10","genres":[{"id":18,"name":"Drama"},{"id":10759,"name":"Action & Adventure"},{"id":35,"name":"Comedy"}],"homepage":"http://ljeto2019.com","id":103061,"in_production":true,"languages":["hr"],"last_air_date":"2019-09-21","last_episode_to_air":{"air_date":"2019-09-21","episode_number":2,"id":2258316,"name":"Ella","overview":"After they arrive in Zadar, the team goes for a swim, where they meet local peers who invite them to a party.","production_code":"","season_number":1,"show_id":103061,"still_path":"/6kg93eIpl4TIEygRiio2LjqUShe.jpg","vote_average":0.0,"vote_count":0},"name":"SUMMER 2019","next_episode_to_air":null,"networks":[{"name":"Vimeo","id":1065,"logo_path":"/lYL7PahejU2LKpMVixqksxnQ448.png","origin_country":""}],"number_of_episodes":2,"number_of_seasons":1,"origin_country":["HR"],"original_language":"hr","original_name":"LJETO 2019","overview":"Four classmates go on a vacation that, once they arrive, derails in every way imaginable.","popularity":0.6,"poster_path":"/sxDsnM7ll5bwr1wDMhoZjPbFND8.jpg","production_companies":[],"seasons":[{"air_date":"2019-09-10","episode_count":2,"id":150001,"name":"Season 1","overview":"A vacation gone awry on several summer nights of 2019.","poster_path":null,"season_number":1}],"status":"Returning Series","type":"Scripted","vote_average":0.0,"vote_count":0}