{"backdrop_path":null,"created_by":[],"episode_run_time":[45],"first_air_date":"2019-01-02","genres":[],"homepage":"","id":101638,"in_production":true,"languages":["en"],"last_air_date":"2020-03-30","last_episode_to_air":{"air_date":"2020-03-30","episode_number":15,"id":2215909,"name":"Loch Ness, Headless Haunting And Prophet Edgar Cayce","overview":"","production_code":"","season_number":2,"show_id":101638,"still_path":null,"vote_average":0.0,"vote_count":0},"name":"Beyond the Unknown","next_episode_to_air":null,"networks":[],"number_of_episodes":32,"number_of_seasons":2,"origin_country":[],"original_language":"en","original_name":"Beyond the Unknown","overview":"Take strange occurrences, weird events, and unexplained happenings and put them all together. That is what you get with Beyond the Unknown. Each episode shows you something different.","popularity":0.6,"poster_path":"/z89HjHf9Ez7cRO8L3RJw97WzOCQ.jpg","production_companies":[],"seasons":[{"air_date":"2019-01-02","episode_count":17,"id":147319,"name":"Season 1","overview":"","poster_path":null,"season_number":1},{"air_date":"2019-12-30","episode_count":15,"id":147332,"name":"Season 2","overview":"","poster_path":null,"season_number":2}],"status":"Returning Series","type":"Scripted","vote_average":0.0,"vote_count":0}