{"backdrop_path":null,"created_by":[],"episode_run_time":[90],"first_air_date":"1981-10-27","genres":[],"homepage":"","id":100026,"in_production":false,"languages":["fr"],"last_air_date":"1981-10-30","last_episode_to_air":{"air_date":"1981-10-30","episode_number":3,"id":2179997,"name":"Episode 3","overview":"","production_code":"","season_number":1,"show_id":100026,"still_path":null,"vote_average":0.0,"vote_count":0},"name":"La double vie de Théophraste Longuet","next_episode_to_air":null,"networks":[{"name":"TF1","id":290,"logo_path":"/fqsd09CrijoGu6qfoNIdgUQmVGO.png","origin_country":"FR"}],"number_of_episodes":3,"number_of_seasons":1,"origin_country":["FR"],"original_language":"fr","original_name":"La double vie de Théophraste Longuet","overview":"","popularity":0.6,"poster_path":"/sjOW1qh3WIQnCXTYOZwayvXW8Xw.jpg","production_companies":[{"id":22123,"logo_path":"/zPTy6QDAlCKGeAALZoFEL3QAlut.png","name":"TF1","origin_country":"FR"},{"id":10714,"logo_path":null,"name":"Télécip","origin_country":""}],"seasons":[{"air_date":"1981-10-27","episode_count":3,"id":144450,"name":"Season 1","overview":"","poster_path":null,"season_number":1}],"status":"Ended","type":"Miniseries","vote_average":0.0,"vote_count":0}