{"backdrop_path":"/p8vc3RzBrv8WylhnMVAxhxeiKoY.jpg","created_by":[],"episode_run_time":[49],"first_air_date":"2014-06-08","genres":[{"id":99,"name":"Documentary"}],"homepage":"https://www.nhk.or.jp/nhkworld/en/tv/cycle/","id":103374,"in_production":true,"languages":["en","ja"],"last_air_date":"2020-04-11","last_episode_to_air":{"air_date":"2020-04-11","episode_number":4,"id":2267272,"name":"Tanegashima and Yakushima - Inspired by Nature","overview":"","production_code":"","season_number":7,"show_id":103374,"still_path":null,"vote_average":0.0,"vote_count":0},"name":"Cycle Around Japan","next_episode_to_air":null,"networks":[{"name":"NHK World","id":3054,"logo_path":null,"origin_country":""}],"number_of_episodes":5,"number_of_seasons":7,"origin_country":["JP"],"original_language":"en","original_name":"Cycle Around Japan","overview":"Come ride with us! Bicycle through the scenery of Japan, stay with locals and discover hidden traditions in a Japan you didn't know existed.","popularity":0.6,"poster_path":"/1Ekp45sXxjVFebrPTcWZ0p4dZSO.jpg","production_companies":[],"seasons":[{"air_date":"2014-06-08","episode_count":1,"id":150627,"name":"Season 1","overview":"","poster_path":null,"season_number":1},{"air_date":null,"episode_count":0,"id":150628,"name":"Season 2","overview":"","poster_path":null,"season_number":2},{"air_date":null,"episode_count":0,"id":150629,"name":"Season 3","overview":"","poster_path":null,"season_number":3},{"air_date":null,"episode_count":0,"id":150630,"name":"Season 4","overview":"","poster_path":null,"season_number":4},{"air_date":null,"episode_count":0,"id":150631,"name":"Season 5","overview":"","poster_path":null,"season_number":5},{"air_date":null,"episode_count":0,"id":150632,"name":"Season 6","overview":"","poster_path":null,"season_number":6},{"air_date":"2020-01-11","episode_count":4,"id":150633,"name":"Season 7","overview":"","poster_path":null,"season_number":7}],"status":"Returning Series","type":"Documentary","vote_average":6.0,"vote_count":1}