{"backdrop_path":"/ogMYcLcavZF5VfqDNj7Qw0UikDC.jpg","created_by":[],"episode_run_time":[],"first_air_date":"2020-04-08","genres":[{"id":10764,"name":"Reality"}],"homepage":"","id":101338,"in_production":true,"languages":[],"last_air_date":"2020-04-08","last_episode_to_air":{"air_date":"2020-04-08","episode_number":1,"id":2209030,"name":"Episode 1","overview":"","production_code":"","season_number":1,"show_id":101338,"still_path":"/gMZt9c9ouL5hVux33JIxNJAJ5F1.jpg","vote_average":0.0,"vote_count":0},"name":"Palazuelos Mi Rey","next_episode_to_air":null,"networks":[],"number_of_episodes":1,"number_of_seasons":1,"origin_country":[],"original_language":"es","original_name":"Palazuelos Mi Rey","overview":"","popularity":0.6,"poster_path":"/uFKEKw79RAethoDIw8b6ZqAkVCe.jpg","production_companies":[],"seasons":[{"air_date":"2020-04-08","episode_count":1,"id":146732,"name":"Season 1","overview":"","poster_path":null,"season_number":1}],"status":"Returning Series","type":"Scripted","vote_average":0.0,"vote_count":0}