{"backdrop_path":null,"created_by":[{"id":2576066,"credit_id":"5e78a1352f3b170014537eef","name":"Henrique Zambelli","gender":0,"profile_path":null}],"episode_run_time":[],"first_air_date":null,"genres":[{"id":18,"name":"Drama"}],"homepage":"","id":100871,"in_production":false,"languages":["pt"],"last_air_date":"2003-10-03","last_episode_to_air":{"air_date":"2003-10-03","episode_number":116,"id":2199062,"name":"Episode 116","overview":"","production_code":"","season_number":1,"show_id":100871,"still_path":null,"vote_average":0.0,"vote_count":0},"name":"Canavial de Paixões","next_episode_to_air":null,"networks":[],"number_of_episodes":1,"number_of_seasons":1,"origin_country":[],"original_language":"pt","original_name":"Canavial de Paixões","overview":"","popularity":0.6,"poster_path":null,"production_companies":[],"seasons":[{"air_date":null,"episode_count":1,"id":145877,"name":"Season 1","overview":"","poster_path":null,"season_number":1}],"status":"Ended","type":"Scripted","vote_average":0.0,"vote_count":0}