{"adult":false,"backdrop_path":null,"belongs_to_collection":null,"budget":0,"genres":[{"id":18,"name":"Drama"}],"homepage":"","id":103707,"imdb_id":"tt1680305","original_language":"en","original_title":"Afghan Luke","overview":"Disheartened when his story about Canadian snipers possibly mutilating corpses in Afghanistan is buried, Luke (Nick Stahl) quits his job but is even more determined to return to Afghanistan to get the real story. With his offbeat buddy, Tom (Nicolas Wright), tagging along, Luke returns to Afghanistan and intends to gather enough evidence to get his old story into print. But he soon finds that the country is an even more dangerous place than when he left. To make matters worse, his old friend and fixer, Mateen (Stephen Lobo) has been hired away by Luke's journalistic nemesis, Imran Sahar (Vik Sahay). Soon the trip for Luke and Tom in Afghanistan turns into a surreal and perilous adventure, a journey into an alternate reality, filtered through a haze of gun smoke.","popularity":4.122,"poster_path":"/d5MJQNy4TxvybZcQAlrPxgdDbXR.jpg","production_companies":[{"id":63964,"logo_path":null,"name":"Afghan Luke Productions","origin_country":""}],"production_countries":[{"iso_3166_1":"CA","name":"Canada"}],"release_date":"2011-09-23","revenue":0,"runtime":100,"spoken_languages":[{"iso_639_1":"en","name":"English"}],"status":"Released","tagline":"","title":"Afghan Luke","video":false,"vote_average":5.4,"vote_count":10}