{"adult":false,"backdrop_path":null,"belongs_to_collection":null,"budget":0,"genres":[{"id":18,"name":"Drama"},{"id":28,"name":"Action"},{"id":53,"name":"Thriller"},{"id":80,"name":"Crime"}],"homepage":"","id":105860,"imdb_id":"tt0071331","original_language":"it","original_title":"La città gioca d'azzardo","overview":"Luca Altieri is a gambler. He likes cards and he is a master in playing poker. He is a cardsharper too. He begins working for \"The President\", who has many gambling houses and everything seems to go well until Luca falls for Maria Luisa. Unfortunately for them, she is the girl of Corrado, the son of \"The President\"...","popularity":1.247,"poster_path":"/hBhMmwuuILiSPqVX3VhZmyXCd9E.jpg","production_companies":[{"id":15868,"logo_path":null,"name":"Medusa Distribuzione","origin_country":""},{"id":1701,"logo_path":null,"name":"Dania Film","origin_country":""}],"production_countries":[{"iso_3166_1":"IT","name":"Italy"}],"release_date":"1975-01-23","revenue":0,"runtime":101,"spoken_languages":[{"iso_639_1":"it","name":"Italiano"}],"status":"Released","tagline":"","title":"Gambling City","video":false,"vote_average":5.5,"vote_count":2}