{"adult":false,"backdrop_path":null,"belongs_to_collection":null,"budget":0,"genres":[{"id":10402,"name":"Music"}],"homepage":"","id":100217,"imdb_id":"","original_language":"pt","original_title":"Fernando e Sorocaba – Acústico na Ópera de Arame","overview":"","popularity":1.124,"poster_path":null,"production_companies":[],"production_countries":[],"release_date":"2011-01-01","revenue":0,"runtime":0,"spoken_languages":[],"status":"Released","tagline":"","title":"Fernando e Sorocaba – Acústico na Ópera de Arame","video":false,"vote_average":10.0,"vote_count":1}