{"adult":false,"backdrop_path":"/bFMVJ0RZ6xHqsZhHQwxc0fPi5h6.jpg","belongs_to_collection":null,"budget":6500000,"genres":[{"id":18,"name":"Drama"},{"id":10752,"name":"War"}],"homepage":"","id":1116,"imdb_id":"tt0460989","original_language":"en","original_title":"The Wind That Shakes the Barley","overview":"In 1920s Ireland young doctor Damien O'Donovan prepares to depart for a new job in a London hospital. As he says his goodbyes at a friend's farm, British Black and Tans arrive, and a young man is killed. Damien joins his brother Teddy in the Irish Republican Army, but political events are soon set in motion that tear the brothers apart.","popularity":7.412,"poster_path":"/hAOrgxv0V29KOQNisenD7TRhfdi.jpg","production_companies":[{"id":12695,"logo_path":"/pZg9WqHoiUqhCzoMwGTcPI6Bs3d.png","name":"Sixteen Films","origin_country":"GB"},{"id":707,"logo_path":null,"name":"Matador Pictures","origin_country":""},{"id":12696,"logo_path":null,"name":"Regent Capital","origin_country":""},{"id":2452,"logo_path":"/6CLoZ59fLPG7UyxQtGTqRevjf58.png","name":"UK Film Council","origin_country":"GB"},{"id":1898,"logo_path":"/8ix6SGlJiyuUDxLBtY8E0PY2G7w.png","name":"Screen Ireland","origin_country":"IE"},{"id":2274,"logo_path":null,"name":"Element Films","origin_country":""},{"id":225,"logo_path":"/cmxkBc3dmwWaIHFCrkXZoAfGoOa.png","name":"BIM Distribuzione","origin_country":"IT"},{"id":19929,"logo_path":null,"name":"EMC Produktion","origin_country":""},{"id":7680,"logo_path":"/uGcInOaHyvFZ337T5OeQKKVjSCJ.png","name":"Tornasol Films","origin_country":"ES"},{"id":744,"logo_path":"/iPQvLZPw7e3T3No0akup0F9o8nV.png","name":"Diaphana Films","origin_country":"FR"},{"id":3012,"logo_path":null,"name":"Pathé Distribution","origin_country":"FR"},{"id":19930,"logo_path":null,"name":"Cinéart","origin_country":""},{"id":19931,"logo_path":null,"name":"TV3 Television Network Ireland","origin_country":""},{"id":19932,"logo_path":null,"name":"Filmcoopi Zürich","origin_country":""},{"id":19933,"logo_path":null,"name":"Oil Flick Films No.2","origin_country":""}],"production_countries":[{"iso_3166_1":"IE","name":"Ireland"},{"iso_3166_1":"GB","name":"United Kingdom"},{"iso_3166_1":"DE","name":"Germany"},{"iso_3166_1":"IT","name":"Italy"},{"iso_3166_1":"ES","name":"Spain"},{"iso_3166_1":"FR","name":"France"},{"iso_3166_1":"BE","name":"Belgium"},{"iso_3166_1":"CH","name":"Switzerland"}],"release_date":"2006-03-24","revenue":22889018,"runtime":127,"spoken_languages":[{"iso_639_1":"en","name":"English"},{"iso_639_1":"ga","name":"Gaeilge"},{"iso_639_1":"la","name":"Latin"}],"status":"Released","tagline":"","title":"The Wind That Shakes the Barley","video":false,"vote_average":7.4,"vote_count":388}