{"adult":false,"backdrop_path":"/jTHoMktPRsdG2llKQExTIxmlMWm.jpg","belongs_to_collection":{"id":187736,"name":"Leningrad Cowboys Collection","poster_path":"/iWzKOYMSVIYhMGTnAGRAdbrzqBZ.jpg","backdrop_path":"/399eIDdzBQ7RRd4BALkozSb2Joc.jpg"},"budget":0,"genres":[{"id":99,"name":"Documentary"},{"id":10402,"name":"Music"}],"homepage":"","id":109485,"imdb_id":"tt0111460","original_language":"en","original_title":"Leningrad Cowboys: Total Balalaika Show","overview":"A 57 minute documentary of a Helsinki concert featuring the Leningrad Cowboys and the Alexandrov Red Army Choir and Ballet, who collaborate on a number of US Rock songs sung in English (like \"Sweet Home, Alabama\") as well as more traditional Russian songs like the \"Volga Boatman\".","popularity":1.832,"poster_path":"/hm8dgzPUbzrR7Q0ZVezVMGc6tAq.jpg","production_companies":[{"id":128462,"logo_path":null,"name":"Provisual","origin_country":""},{"id":706,"logo_path":null,"name":"Sputnik","origin_country":"FI"}],"production_countries":[{"iso_3166_1":"FI","name":"Finland"}],"release_date":"1994-07-04","revenue":0,"runtime":57,"spoken_languages":[{"iso_639_1":"en","name":"English"},{"iso_639_1":"ru","name":"Pусский"},{"iso_639_1":"fi","name":"suomi"},{"iso_639_1":"fr","name":"Français"}],"status":"Released","tagline":"","title":"Leningrad Cowboys: Total Balalaika Show","video":false,"vote_average":6.1,"vote_count":7}