{"adult":false,"backdrop_path":null,"belongs_to_collection":null,"budget":0,"genres":[],"homepage":"","id":103553,"imdb_id":"tt2325791","original_language":"nl","original_title":"Katherine Jenkins: Believe Live from the O2","overview":"","popularity":0.6,"poster_path":"/dn0XP7cU44TMgEnG0qyzMYImUmE.jpg","production_companies":[],"production_countries":[],"release_date":"2010-11-08","revenue":0,"runtime":0,"spoken_languages":[],"status":"Released","tagline":"","title":"Katherine Jenkins: Believe Live from the O2","video":false,"vote_average":0.0,"vote_count":0}