{"adult":false,"backdrop_path":null,"belongs_to_collection":null,"budget":0,"genres":[{"id":10402,"name":"Music"},{"id":99,"name":"Documentary"}],"homepage":"","id":110286,"imdb_id":"tt1825675","original_language":"en","original_title":"Bee Gees: In Our Own Time","overview":"This documentary on the life and career of The Bee Gees mixes archival performance footage with intimate home movies to paint a portrait of the three brothers who became one of the biggest selling music acts in the world.","popularity":1.4,"poster_path":"/g4v78jRkCytMQ60glelnqrjzl56.jpg","production_companies":[],"production_countries":[],"release_date":"2010-11-11","revenue":0,"runtime":116,"spoken_languages":[{"iso_639_1":"en","name":"English"}],"status":"Released","tagline":"","title":"Bee Gees: In Our Own Time","video":false,"vote_average":8.0,"vote_count":1}