{"adult":false,"backdrop_path":"/dY6oEH886dRIpZU3baj4FJfSHdw.jpg","belongs_to_collection":null,"budget":0,"genres":[{"id":28,"name":"Action"},{"id":37,"name":"Western"}],"homepage":"","id":104974,"imdb_id":"tt0066886","original_language":"en","original_title":"Captain Apache","overview":"An Indian discovers plans to assassinate the president when he was investigating another murder.","popularity":5.668,"poster_path":"/rfC8xYW7ZcQ3hvTKcLqPqXLsqIS.jpg","production_companies":[{"id":13947,"logo_path":null,"name":"Benmar Productions","origin_country":"GB"},{"id":7730,"logo_path":null,"name":"Scotia International","origin_country":""}],"production_countries":[{"iso_3166_1":"ES","name":"Spain"},{"iso_3166_1":"GB","name":"United Kingdom"}],"release_date":"1971-10-27","revenue":0,"runtime":94,"spoken_languages":[{"iso_639_1":"en","name":"English"}],"status":"Released","tagline":"They Trailed Him...Tailed Him...Tried to Nail Him...NO WAY!!!","title":"Captain Apache","video":false,"vote_average":4.4,"vote_count":14}