{"adult":false,"backdrop_path":null,"belongs_to_collection":null,"budget":0,"genres":[{"id":28,"name":"Action"},{"id":18,"name":"Drama"}],"homepage":"","id":112015,"imdb_id":"tt0344507","original_language":"en","original_title":"Two Timer","overview":"Viveca is happily married to Cholo, a renowned and respected psychiatrist. Unknown to many, Viveca, has long been leading a double life. She has an appetite for men, for quick, and sometimes very dangerous sexual adventures, be it real or fantasy. There is no question in her mind how much she loves her family. Viveca had a one-time affair with Andre, a DJ who is bored with his life. He surrounds himself with toys from drugs to race cars to Dahlia, who is more a girl toy than a girlfriend. A one night stand with Viveca gives Andre the speed he has been looking for: a forbidden love affair with a very attractive married woman. He pursues Viveca like there is no tomorrow. Viveca tries to distance herself from Andre, but he proves to be too stubborn for her. Complications upon complications set it. Should Viveca remain secretive of what is happening or continue living a life of deceit.","popularity":2.088,"poster_path":"/jTwuYdaVdp70W1y6yZvg6cvcsVa.jpg","production_companies":[{"id":8238,"logo_path":"/3f3SS3sep9V3Nf7RAxNd5UUEw1E.png","name":"Regal Entertainment","origin_country":"PH"}],"production_countries":[{"iso_3166_1":"PH","name":"Philippines"}],"release_date":"2002-11-06","revenue":0,"runtime":98,"spoken_languages":[{"iso_639_1":"tl","name":""}],"status":"Released","tagline":"","title":"Two Timer","video":false,"vote_average":0.0,"vote_count":0}