{"adult":false,"backdrop_path":null,"belongs_to_collection":null,"budget":0,"genres":[{"id":99,"name":"Documentary"}],"homepage":"","id":110957,"imdb_id":"tt1922767","original_language":"fr","original_title":"Tous au Larzac","overview":"Documentary","popularity":1.898,"poster_path":null,"production_companies":[{"id":836,"logo_path":"/93zzVd8ijSExx6DhVI4Xqj8WmOJ.png","name":"Elzévir Films","origin_country":"FR"}],"production_countries":[{"iso_3166_1":"FR","name":"France"}],"release_date":"2011-11-23","revenue":0,"runtime":120,"spoken_languages":[{"iso_639_1":"fr","name":"Français"}],"status":"Released","tagline":"","title":"Tous au Larzac","video":false,"vote_average":6.9,"vote_count":12}