{"adult":false,"backdrop_path":null,"belongs_to_collection":null,"budget":0,"genres":[{"id":37,"name":"Western"}],"homepage":"","id":113031,"imdb_id":"tt0059038","original_language":"it","original_title":"Cinque dollari per Ringo","overview":"Sheriff Lester Sands travels to Lindsborg in the hope of finding a gang of outlaws operating in the region. He suspects that they hide there because recently they raided the bank of a neighboring village. And during the robbery,  the director was wounded. His daughter Miriam, accompanied by five bank guards has followed the trail of the assailants there. With this event and the attitude of the village mayor, the sheriff and his suspicions are confirmed and he expects that sooner or later he will face these gunmen.","popularity":3.149,"poster_path":"/4dwU3bFKbWHEdfDWpPmP0xHXAaG.jpg","production_companies":[{"id":71846,"logo_path":null,"name":"Moncayo Films","origin_country":""},{"id":4779,"logo_path":null,"name":"Cinematografica Associati (CI.AS.)","origin_country":"IT"},{"id":67688,"logo_path":null,"name":"I.F.I. España S.A","origin_country":""}],"production_countries":[{"iso_3166_1":"IT","name":"Italy"},{"iso_3166_1":"ES","name":"Spain"}],"release_date":"1966-07-23","revenue":0,"runtime":81,"spoken_languages":[{"iso_639_1":"it","name":"Italiano"}],"status":"Released","tagline":"","title":"Five Dollars for Ringo","video":false,"vote_average":0.0,"vote_count":0}