{"adult":false,"backdrop_path":"/kDnIMnIDXhi1V8JoKHzxkbaR0su.jpg","belongs_to_collection":null,"budget":0,"genres":[{"id":18,"name":"Drama"},{"id":10749,"name":"Romance"},{"id":10752,"name":"War"}],"homepage":"","id":103938,"imdb_id":"tt0024675","original_language":"en","original_title":"Today We Live","overview":"The two lovers are living together and are not married as they hesitantly explain to her brother. They had made a promise as children to get married when they grew up, but they \"didn't wait.\" It's an important plot point as it drives Cooper's actions when he discovers that Crawford and Young are living in sin.","popularity":5.43,"poster_path":"/ib4fOwF3NgI8hOExotSztNvzgKU.jpg","production_companies":[{"id":21,"logo_path":"/mjofSXiHpG5t6KYmU4l4FrUhT7m.png","name":"Metro-Goldwyn-Mayer","origin_country":"US"}],"production_countries":[{"iso_3166_1":"US","name":"United States of America"}],"release_date":"1933-03-03","revenue":0,"runtime":113,"spoken_languages":[{"iso_639_1":"es","name":"Español"},{"iso_639_1":"en","name":"English"}],"status":"Released","tagline":"","title":"Today We Live","video":false,"vote_average":6.6,"vote_count":9}