{"adult":false,"backdrop_path":"/cupzS0aVTGsnMR4pbmveyA8R8B3.jpg","belongs_to_collection":null,"budget":0,"genres":[{"id":9648,"name":"Mystery"},{"id":53,"name":"Thriller"}],"homepage":"","id":110419,"imdb_id":"tt0067907","original_language":"en","original_title":"Unman, Wittering and Zigo","overview":"A new school teacher learns that the previous teacher was killed by his pupils, and he fears the same will happen to him","popularity":2.379,"poster_path":"/wxVbQvHLOWyPDMk4ceN4VjY9emK.jpg","production_companies":[{"id":4,"logo_path":"/fycMZt242LVjagMByZOLUGbCvv3.png","name":"Paramount","origin_country":"US"},{"id":35411,"logo_path":null,"name":"Mediarts","origin_country":""},{"id":35412,"logo_path":null,"name":"Hemmings","origin_country":""}],"production_countries":[{"iso_3166_1":"GB","name":"United Kingdom"}],"release_date":"1971-07-11","revenue":0,"runtime":102,"spoken_languages":[{"iso_639_1":"en","name":"English"}],"status":"Released","tagline":"if you're curious about terror…","title":"Unman, Wittering and Zigo","video":false,"vote_average":6.9,"vote_count":11}