{"adult":false,"backdrop_path":null,"belongs_to_collection":null,"budget":600000,"genres":[{"id":27,"name":"Horror"}],"homepage":"http://magnetreleasing.com/2359/","id":107227,"imdb_id":"tt2100376","original_language":"zh","original_title":"23:59","overview":"An army recruit was found dead during a 24km road march. After the death of the recruit, strange things started to happen, haunting all the soldiers in the barracks.","popularity":4.146,"poster_path":"/sQGBK2mvw3x07MmwRR2J6fDADZ5.jpg","production_companies":[{"id":128953,"logo_path":null,"name":"Gorylah Pictures","origin_country":""},{"id":7711,"logo_path":null,"name":"Clover Films","origin_country":""},{"id":22482,"logo_path":null,"name":"Grand Brilliance","origin_country":""},{"id":55802,"logo_path":"/l1lnXmGse9lO7Pz1Z49SrSk3Y6J.png","name":"MM2 Entertainment","origin_country":"SG"}],"production_countries":[{"iso_3166_1":"MY","name":"Malaysia"},{"iso_3166_1":"SG","name":"Singapore"}],"release_date":"2011-11-03","revenue":1208479,"runtime":78,"spoken_languages":[{"iso_639_1":"zh","name":"普通话"},{"iso_639_1":"en","name":"English"},{"iso_639_1":"ms","name":"Bahasa melayu"}],"status":"Released","tagline":"","title":"23:59","video":false,"vote_average":4.5,"vote_count":27}