{"adult":false,"backdrop_path":null,"belongs_to_collection":null,"budget":0,"genres":[{"id":35,"name":"Comedy"}],"homepage":null,"id":100820,"imdb_id":"tt0457279","original_language":"en","original_title":"Are You Ready for Love?","overview":"","popularity":1.025,"poster_path":"/oskEsgOrPCdJpRDIiuhPixDnWqU.jpg","production_companies":[],"production_countries":[],"release_date":"2006-12-09","revenue":0,"runtime":null,"spoken_languages":[{"iso_639_1":"en","name":"English"}],"status":"Released","tagline":"","title":"Are You Ready for Love?","video":false,"vote_average":0.0,"vote_count":0}