{"adult":false,"backdrop_path":"/d2UVqqm9SYXKzuYEw6gmvCdqRfk.jpg","belongs_to_collection":null,"budget":3000000,"genres":[{"id":18,"name":"Drama"},{"id":10749,"name":"Romance"}],"homepage":"","id":102353,"imdb_id":"tt0172234","original_language":"hi","original_title":"चाहत","overview":"Roop and his father come to the city for medical treatment where Reshma falls in love with Roop. However, Roop loves Pooja but when Reshma threatens to kill herself, Roop agrees to marry her.","popularity":3.898,"poster_path":"/cn3gL1s7ZshDUTjcZ0W4JCyBBc6.jpg","production_companies":[{"id":116165,"logo_path":null,"name":"Bhatt Productions","origin_country":""}],"production_countries":[],"release_date":"1996-06-06","revenue":7100000,"runtime":155,"spoken_languages":[{"iso_639_1":"hi","name":"हिन्दी"}],"status":"Released","tagline":"Moments of love, moments of pain.","title":"Chaahat","video":false,"vote_average":7.1,"vote_count":14}