{"adult":false,"backdrop_path":null,"belongs_to_collection":null,"budget":0,"genres":[{"id":18,"name":"Drama"}],"homepage":"","id":102331,"imdb_id":"tt1124001","original_language":"en","original_title":"Vasermil","overview":"Vasermil tells the story of three teenagers who live in the same tough neighborhood, growing up in an unforgiving environment, pinning their hopes on football as a way out. Shlomi lives with his widowed mother, little sister, and step-father and works as a pizza delivery boy. Adiel, of Ethiopian descent, has to look after his young brother and sick mother. Dima, a new immigrant from Russia, has a father who is unemployed and a mother who works as a cleaning lady. The three teens are recruited by the coach of the local football team. Learning to work together as a team is the key to success in the tournament and success in the tournament means getting noticed by the scouts of the local football empire. In order to win the tournament they will have to play as a team, overcome their differences, get over their sense of inferiority and prejudice.","popularity":2.331,"poster_path":null,"production_companies":[{"id":26629,"logo_path":null,"name":"Transfax Film Productions","origin_country":""}],"production_countries":[{"iso_3166_1":"IL","name":"Israel"}],"release_date":"2007-10-25","revenue":0,"runtime":93,"spoken_languages":[{"iso_639_1":"ru","name":"Pусский"},{"iso_639_1":"he","name":"עִבְרִית"},{"iso_639_1":"am","name":""},{"iso_639_1":"sw","name":"Kiswahili"}],"status":"Released","tagline":"","title":"Vasermil","video":false,"vote_average":7.2,"vote_count":5}