{"adult":false,"backdrop_path":null,"belongs_to_collection":null,"budget":0,"genres":[{"id":37,"name":"Western"}],"homepage":"","id":105536,"imdb_id":"tt0047501","original_language":"en","original_title":"Sitting Bull","overview":"Chief Sitting Bull of the Sioux tribe is forced by the Indian-hating General Custer to react with violence, resulting in the famous Last Stand at Little Bighorn. Parrish, a friend to the Sioux, tries to prevent the bloodshed, but is court- martialed for \"collaborating\" with the enemy. Sitting Bull, however, manages to intercede with President Grant on Parrish's behalf. Written by Jim Beaver","popularity":4.795,"poster_path":"/cGxSpllI1NzBaLyf2q0Xt1DALxu.jpg","production_companies":[{"id":21529,"logo_path":null,"name":"W.R. Frank Productions","origin_country":""}],"production_countries":[{"iso_3166_1":"US","name":"United States of America"},{"iso_3166_1":"MX","name":"Mexico"}],"release_date":"1954-10-06","revenue":0,"runtime":105,"spoken_languages":[{"iso_639_1":"en","name":"English"}],"status":"Released","tagline":"","title":"Sitting Bull","video":false,"vote_average":4.5,"vote_count":12}