{"adult":false,"backdrop_path":null,"belongs_to_collection":null,"budget":0,"genres":[{"id":18,"name":"Drama"},{"id":10749,"name":"Romance"}],"homepage":"","id":109545,"imdb_id":"tt0361437","original_language":"es","original_title":"Chiche Bombon","overview":"Love and morality collide in a small Argentinean town when teenage Marianito (Federico Canepa) falls in love with Chiche (Andrea Galante), who's 10 years his senior. When she becomes pregnant, the two decide to make a life together despite hostility from family and friends. But can love survive in the face of so much opposition? Written and directed by Fernando Musa, this intense character study co-stars Ingrid Pelicori and Enrique Liporace.","popularity":0.699,"poster_path":null,"production_companies":[],"production_countries":[{"iso_3166_1":"AR","name":"Argentina"}],"release_date":"2004-10-21","revenue":0,"runtime":94,"spoken_languages":[{"iso_639_1":"es","name":"Español"}],"status":"Released","tagline":"In the neighborhood, you talk about them.","title":"Chiche Bombon","video":false,"vote_average":5.5,"vote_count":2}