{"adult":false,"backdrop_path":null,"belongs_to_collection":null,"budget":0,"genres":[{"id":14,"name":"Fantasy"},{"id":18,"name":"Drama"},{"id":35,"name":"Comedy"}],"homepage":"","id":107282,"imdb_id":"tt0069226","original_language":"en","original_title":"Savages","overview":"A tribe of primitive \"mudpeople\" encounter a croquet ball, rolling through their forest. Following it, they find themselves on a vast, deserted Long Island estate. Entering, they begin to become civilized and assume the stereotypical roles and dress of people at a weekend party. There follows an allegory of upper-class behavior. At last, they begin to devolve toward their original status, and after a battle at croquet, they disappear into the woods.","popularity":1.84,"poster_path":"/lvOpUiYhZQR6DE0AmTY7b4i7xHy.jpg","production_companies":[{"id":2370,"logo_path":null,"name":"Merchant Ivory Productions","origin_country":"US"}],"production_countries":[{"iso_3166_1":"US","name":"United States of America"}],"release_date":"1972-06-27","revenue":0,"runtime":106,"spoken_languages":[{"iso_639_1":"de","name":"Deutsch"},{"iso_639_1":"en","name":"English"}],"status":"Released","tagline":"","title":"Savages","video":false,"vote_average":5.3,"vote_count":3}