{"adult":false,"backdrop_path":null,"belongs_to_collection":{"id":221540,"name":"Freeway Speedway Collection","poster_path":"/l4fdfnQbuW6V6q1nZaM4MKUVraN.jpg","backdrop_path":null},"budget":0,"genres":[],"homepage":"","id":108657,"imdb_id":"","original_language":"ja","original_title":"首都高速トライアルMAX","overview":"Sendo, champion of the Osaka Expressway is challenged to a race by Tatsuya Shikiba, champion racer of the Metropolitan Expressway. During their race, Sendo crashes and injures himself. Two months later, when Sendo is released from the hospital, je looks to find Tatsuya for a rematch. Tatsuya has given up racing after the death of his friend Kazuki during a race, but Sendo wants his rematch. Kazuki’s sister, though distraught with the loss of her brother, decides to help Tatsuya get over his fear of racing and get back on the road to live out his and Kazuki’s dream of being a race car driver.","popularity":0.6,"poster_path":null,"production_companies":[{"id":955,"logo_path":"/5xnXD3PJI1HqOJceSAKZ3fDqO1V.png","name":"Nikkatsu Corporation","origin_country":"JP"},{"id":74801,"logo_path":null,"name":"Nikkatsu Video","origin_country":""}],"production_countries":[{"iso_3166_1":"JP","name":"Japan"}],"release_date":"1996-02-09","revenue":0,"runtime":95,"spoken_languages":[{"iso_639_1":"ja","name":"日本語"}],"status":"Released","tagline":"","title":"Megalopolis Express Way Trial Max","video":false,"vote_average":0.0,"vote_count":0}