{"adult":false,"backdrop_path":null,"belongs_to_collection":null,"budget":0,"genres":[{"id":99,"name":"Documentary"},{"id":10402,"name":"Music"}],"homepage":"","id":101021,"imdb_id":"tt0495138","original_language":"es","original_title":"La leyenda del tiempo","overview":"A documentary/fiction mix inspired by the flamenco singer Camarón.","popularity":1.495,"poster_path":"/vOA0p2ZDUmukRYa8wMMOFi8UtVL.jpg","production_companies":[{"id":91641,"logo_path":null,"name":"De Palacio Films","origin_country":""},{"id":3137,"logo_path":null,"name":"Jaleo Films","origin_country":""},{"id":29862,"logo_path":null,"name":"Mallerich Audiovisuales S.L.","origin_country":""}],"production_countries":[{"iso_3166_1":"ES","name":"Spain"}],"release_date":"2006-06-02","revenue":0,"runtime":109,"spoken_languages":[{"iso_639_1":"ja","name":"日本語"},{"iso_639_1":"es","name":"Español"}],"status":"Released","tagline":"","title":"The Legend of Time","video":false,"vote_average":6.3,"vote_count":4}