{"adult":false,"backdrop_path":"/57V0nYKT87c3nZuLQbtfE0XYsRA.jpg","belongs_to_collection":null,"budget":0,"genres":[{"id":35,"name":"Comedy"}],"homepage":"","id":105499,"imdb_id":"tt0187567","original_language":"fr","original_title":"Une journée de merde","overview":"This is an important day for Marc Chanois, an insurance advisor heading toward middle age: it's his fiancée Sabine's birthday, her parents arrive in Paris and Marc will meet them for dinner to announce the engagement (her father can't stand him), he's bought Sabine a Spitfire, and his most important client is to sign a policy. But, as the day wears on, he's vexed by an incompetent secretary, the unexpected return of a girlfriend he hasn't seen in five years, squatters who use his office at night, the jealous former lover of a flight attendant who lives in the building, and his boss's unexpected return from a Swiss clinic. Will he reach Sabine in one piece?","popularity":1.035,"poster_path":"/jAVkaUOMIxt7QQPVdJ8khj3WqOF.jpg","production_companies":[],"production_countries":[{"iso_3166_1":"FR","name":"France"}],"release_date":"1999-03-03","revenue":0,"runtime":95,"spoken_languages":[{"iso_639_1":"fr","name":"Français"}],"status":"Released","tagline":"","title":"Une journée de merde","video":false,"vote_average":5.8,"vote_count":3}