{"adult":false,"backdrop_path":null,"belongs_to_collection":null,"budget":0,"genres":[{"id":10402,"name":"Music"}],"homepage":"","id":102957,"imdb_id":"tt0486680","original_language":"en","original_title":"Die Ärzte: Die Band, die sie Pferd nannten","overview":"\"Die Band, die sie Pferd nannten\" is the fourth DVD by the Berlin punk band Die Ärzte. It was released as the DVD to the 2004 tour \"Jenseits der Grenze des Zumutbaren\", that promoted the album \"Geräusch\".","popularity":1.209,"poster_path":"/t9HtqeYIDB4GfFu794GpPbEIbgW.jpg","production_companies":[{"id":9339,"logo_path":"/hwEpOrIYH7G4Rolt7s2thYquJnD.png","name":"Universal Music Group","origin_country":"US"}],"production_countries":[{"iso_3166_1":"DE","name":"Germany"}],"release_date":"2004-08-22","revenue":0,"runtime":360,"spoken_languages":[{"iso_639_1":"de","name":"Deutsch"}],"status":"Released","tagline":"","title":"Die Ärzte: Die Band, die sie Pferd nannten","video":true,"vote_average":0.0,"vote_count":0}