{"adult":false,"backdrop_path":null,"belongs_to_collection":null,"budget":0,"genres":[{"id":35,"name":"Comedy"}],"homepage":"","id":112281,"imdb_id":"tt2165254","original_language":"pt","original_title":"A Última Famel","overview":"The story depicts the disappearance of the legendary motorcycle industry in the region Bairrada in Portugal, the famous Famel / Zundap.","popularity":0.6,"poster_path":"/kDG3CF8xcb4yp2NuTrdvWxKsQ92.jpg","production_companies":[],"production_countries":[{"iso_3166_1":"PT","name":"Portugal"}],"release_date":"2010-02-25","revenue":0,"runtime":65,"spoken_languages":[{"iso_639_1":"pt","name":"Português"}],"status":"Released","tagline":"","title":"A Última Famel","video":false,"vote_average":7.0,"vote_count":2}