{"adult":false,"backdrop_path":null,"belongs_to_collection":null,"budget":6830000,"genres":[],"homepage":"","id":100075,"imdb_id":"tt0116091","original_language":"fr","original_title":"Les 2 papas et la maman","overview":"Jérôme and Delphine want a child but Jerome is sterile. They then ask the best friend of Jerome, Salim, to be the donor for artificial insemination of the mother...","popularity":2.026,"poster_path":"/eA6gGjwq8W43SVabikKDLDIYhFS.jpg","production_companies":[],"production_countries":[{"iso_3166_1":"FR","name":"France"}],"release_date":"1996-04-24","revenue":0,"runtime":90,"spoken_languages":[{"iso_639_1":"fr","name":"Français"}],"status":"Released","tagline":"","title":"Two Dads and One Mom","video":false,"vote_average":2.9,"vote_count":7}