{"adult":false,"backdrop_path":null,"belongs_to_collection":null,"budget":0,"genres":[],"homepage":"","id":110026,"imdb_id":"tt0026773","original_language":"en","original_title":"The New Adventures of Tarzan","overview":"Tarzan, who has returned to Africa after living in England, sets off to Guatemala in search of an old friend who may have survived a plane crash there. Also in Guatemala are Ula Vale and Major Martling who are out to find the riches of the Green Goddess. They join forces after they learn that a competitor, Raglan, has already set out ahead of them. Tarzan has to rescue everyone after they are taken prisoner. When they get to the hidden city, Tarzan finds his friend alive and the fabulous treasure.","popularity":0.621,"poster_path":"/tiww3s2ttucIjpq9w0NM5eEDjxx.jpg","production_companies":[{"id":73531,"logo_path":null,"name":"Burroughs-Tarzan Pictures Inc.","origin_country":""}],"production_countries":[{"iso_3166_1":"US","name":"United States of America"}],"release_date":"1935-05-21","revenue":0,"runtime":70,"spoken_languages":[{"iso_639_1":"en","name":"English"}],"status":"Released","tagline":"","title":"The New Adventures of Tarzan","video":false,"vote_average":3.0,"vote_count":1}