{"adult":false,"backdrop_path":null,"belongs_to_collection":null,"budget":0,"genres":[{"id":14,"name":"Fantasy"},{"id":28,"name":"Action"}],"homepage":"","id":106560,"imdb_id":"","original_language":"en","original_title":"Pedang Naga Pasa","overview":"Crazy mix of action, fantasy and martial arts around a magic sword and revenge, with flying sorcerers, duels of laser beams, endless swordfights and many more. A lot of fun is guaranteed.","popularity":0.84,"poster_path":null,"production_companies":[],"production_countries":[{"iso_3166_1":"ID","name":"Indonesia"}],"release_date":"1990-01-01","revenue":0,"runtime":80,"spoken_languages":[{"iso_639_1":"id","name":"Bahasa indonesia"}],"status":"Released","tagline":"","title":"Pedang Naga Pasa","video":false,"vote_average":0.0,"vote_count":0}