{"adult":false,"backdrop_path":null,"belongs_to_collection":null,"budget":0,"genres":[{"id":27,"name":"Horror"},{"id":53,"name":"Thriller"}],"homepage":"","id":108873,"imdb_id":"tt0090148","original_language":"en","original_title":"Terminal Choice","overview":"A patient in an hospital dies under mysterious circumstances. The attending doctor Frank Holt gets under suspect - he'd been fired already from his last position due to malpractice. For his defense he investigates with help of doctor Anna Lang. Soon they find out that half of their colleagues were betting on the patient's diagnosis - was someone trying to increase his chances? But when Frank's friend, dissector Mary Connor, becomes deadly sick, he suspects there's even more to it.","popularity":1.55,"poster_path":"/tdle6S7rxAC1XWKOlYcvW8okvdr.jpg","production_companies":[{"id":20163,"logo_path":null,"name":"Magder Film Productions","origin_country":""}],"production_countries":[{"iso_3166_1":"CA","name":"Canada"}],"release_date":"1985-05-10","revenue":0,"runtime":97,"spoken_languages":[{"iso_639_1":"en","name":"English"}],"status":"Released","tagline":"At Dodson Clinic, there's a chance you may not recover. The doctors are betting on it","title":"Terminal Choice","video":false,"vote_average":0.0,"vote_count":0}