{"adult":false,"backdrop_path":"/vqrpj0YSx1kWyEngC85jsMJepNp.jpg","belongs_to_collection":null,"budget":0,"genres":[{"id":99,"name":"Documentary"},{"id":18,"name":"Drama"}],"homepage":"","id":104951,"imdb_id":"tt0123962","original_language":"fr","original_title":"Lettre à Freddy Buache","overview":"Godard addresses an audiovisual letter to Freddy Buache. He films Lausanne and talks of what cinema is: the light, the movements and the colors.","popularity":2.2,"poster_path":"/bi3xED8eEo8gOrlhODzsCxHgA4m.jpg","production_companies":[],"production_countries":[{"iso_3166_1":"CH","name":"Switzerland"}],"release_date":"1982-01-01","revenue":0,"runtime":11,"spoken_languages":[{"iso_639_1":"fr","name":"Français"}],"status":"Released","tagline":"","title":"Letter to Freddy Buache","video":false,"vote_average":5.4,"vote_count":5}