{"adult":false,"backdrop_path":null,"belongs_to_collection":null,"budget":0,"genres":[],"homepage":"","id":113191,"imdb_id":"tt0053590","original_language":"es","original_title":"Ama Rosa","overview":"Rosa gives birth to a child who, by circumstances of life, is given for adoption to a wealthy family who lost theirs during childbirth. Soon, Rosa will be working for the new family of his son and, so, without anyone knowing, will give him all her love.","popularity":0.6,"poster_path":"/lqzCX3F6wNAiRgbZnhXqaysddIZ.jpg","production_companies":[],"production_countries":[],"release_date":"1960-04-17","revenue":0,"runtime":99,"spoken_languages":[{"iso_639_1":"es","name":"Español"}],"status":"Released","tagline":"","title":"Ama Rosa","video":false,"vote_average":0.0,"vote_count":0}