{"adult":false,"backdrop_path":null,"belongs_to_collection":null,"budget":0,"genres":[{"id":18,"name":"Drama"},{"id":10749,"name":"Romance"},{"id":28,"name":"Action"},{"id":27,"name":"Horror"}],"homepage":"","id":105846,"imdb_id":"tt0269338","original_language":"de","original_title":"Hot Love","overview":"A guy loves a girl and he sees her one day with another guy, he freaks out, commits suicide, then she has a baby.","popularity":0.805,"poster_path":null,"production_companies":[{"id":58145,"logo_path":null,"name":"J.B. Films","origin_country":""}],"production_countries":[{"iso_3166_1":"DE","name":"Germany"}],"release_date":"1985-01-01","revenue":0,"runtime":40,"spoken_languages":[],"status":"Released","tagline":"","title":"Hot Love","video":false,"vote_average":5.5,"vote_count":4}