{"adult":false,"backdrop_path":null,"belongs_to_collection":null,"budget":0,"genres":[],"homepage":"","id":105335,"imdb_id":"tt0224633","original_language":"fr","original_title":"L'affaire Dreyfus, bagarre entre journalistes","overview":"During an interval in the proceedings of the court martial, the journalists enter into an animated discussion, resulting in a dispute between Arthur Meyer of the 'Gaulois', and Mme. Severine of the 'Fronde', resulting in a fight between Dreyfusards and Anti-Dreyfusards, in which canes and chairs are brought down upon the heads of many. The room is finally cleared by the gendarmes.","popularity":1.246,"poster_path":"/k6AuHhctTqQPV5miYfQ97SEadC5.jpg","production_companies":[{"id":45867,"logo_path":null,"name":"Star Film Company","origin_country":""}],"production_countries":[{"iso_3166_1":"FR","name":"France"}],"release_date":"1899-01-01","revenue":0,"runtime":1,"spoken_languages":[],"status":"Released","tagline":"","title":"The Fight of Reporters","video":false,"vote_average":4.8,"vote_count":17}