{"adult":false,"backdrop_path":null,"belongs_to_collection":null,"budget":0,"genres":[{"id":99,"name":"Documentary"},{"id":10752,"name":"War"}],"homepage":"","id":101595,"imdb_id":"tt0173827","original_language":"en","original_title":"The Fight for the Sky","overview":"Documentary detailing the activities of American fighter escort pilots during bombing raids over Germany.","popularity":0.696,"poster_path":null,"production_companies":[{"id":9386,"logo_path":null,"name":"First Motion Pictures Unit US Army Air Forces","origin_country":""}],"production_countries":[{"iso_3166_1":"US","name":"United States of America"}],"release_date":"1945-06-21","revenue":0,"runtime":20,"spoken_languages":[],"status":"Released","tagline":"","title":"The Fight for the Sky","video":false,"vote_average":5.0,"vote_count":2}