{"adult":false,"backdrop_path":null,"belongs_to_collection":null,"budget":0,"genres":[{"id":27,"name":"Horror"}],"homepage":"","id":104411,"imdb_id":"tt1329273","original_language":"zh","original_title":"凶魅","overview":"Xiaoyun loses his entire family in a car accident. A few years later she was adopted by a couple who believe that a child can get to their ever more rooted relationship. It will not be long before strange things start happening around Xiaoyun.","popularity":0.626,"poster_path":null,"production_companies":[{"id":13278,"logo_path":null,"name":"Long Shong Entertainment Multimedia Company","origin_country":""}],"production_countries":[{"iso_3166_1":"TW","name":"Taiwan"}],"release_date":"2008-11-06","revenue":0,"runtime":103,"spoken_languages":[{"iso_639_1":"zh","name":"普通话"}],"status":"Released","tagline":"","title":"Good Will Evil","video":false,"vote_average":1.0,"vote_count":1}