{"adult":false,"backdrop_path":null,"belongs_to_collection":null,"budget":0,"genres":[{"id":10402,"name":"Music"}],"homepage":"","id":105377,"imdb_id":"tt0251776","original_language":"en","original_title":"Kitaro: Kojiki - A Story in Concert","overview":"Kitaro has long been one of the leading lights of new age music. This program captures him in a 1990 live appearance from one of his increasingly rare concert tours, performing selections from Kojiki: A Story in Concert, a musical adaptation of legends from traditional Japanese folklore","popularity":0.6,"poster_path":"/ttyGqeVcLes2ahAInqPiMdKQTZ2.jpg","production_companies":[],"production_countries":[],"release_date":"1990-01-01","revenue":0,"runtime":54,"spoken_languages":[],"status":"Released","tagline":"","title":"Kitaro: Kojiki - A Story in Concert","video":false,"vote_average":5.5,"vote_count":3}